server.py
mohua-0.1.0.dist-info/METADATA
mohua-0.1.0.dist-info/WHEEL
mohua-0.1.0.dist-info/top_level.txt
mohua-0.1.0.dist-info/RECORD
