Metadata-Version: 2.4
Name: mohua
Version: 0.1.0
Summary: Add your description here
Requires-Python: >=3.12
Requires-Dist: fastmcp>=2.11.3
Requires-Dist: mcp[cli]>=1.13.0
